LICENSE
README.md
setup.py
pyxml/__init__.py
pyxml/_tokenize.py
pyxml/builder.py
pyxml/element.py
pyxml/escape.py
pyxml/etree.py
pyxml/lexer.py
pyxml/parser.py
pyxml/compat/ElementPath.py
pyxml/compat/ElementTree.py
pyxml/compat/__init__.py
pyxml/html/__init__.py
pyxml/html/parser.py
pyxml/tests/__init__.py
pyxml/tests/builder.py
pyxml/tests/html.py
pyxml/tests/parser.py
pyxml/tests/xpath.py
pyxml/xpath/__init__.py
pyxml/xpath/engine.py
pyxml/xpath/functions.py
pyxml/xpath/lexer.py
pyxml3.egg-info/PKG-INFO
pyxml3.egg-info/SOURCES.txt
pyxml3.egg-info/dependency_links.txt
pyxml3.egg-info/requires.txt
pyxml3.egg-info/top_level.txt