Metadata-Version: 2.1
Name: pyxml3
Version: 0.0.2
Summary: Pure python3 Alternative to stdlib xml.etree with HTML support
Home-page: https://github.com/imgurbot12/pyxml
Author: Andrew Scott
Author-email: imgurbot12@gmail.com
License: MIT
Classifier: Programming Language :: Python :: 3
Classifier: License :: OSI Approved :: MIT License
Classifier: Operating System :: OS Independent
Requires-Python: >=3.6
License-File: LICENSE
